privy_mcp/__init__.py
privy_mcp/__main__.py
privy_mcp/client.py
privy_mcp/server.py
privy_mcp_server-0.1.2.dist-info/licenses/LICENSE
privy_mcp_server-0.1.2.dist-info/METADATA
privy_mcp_server-0.1.2.dist-info/WHEEL
privy_mcp_server-0.1.2.dist-info/entry_points.txt
privy_mcp_server-0.1.2.dist-info/top_level.txt
privy_mcp_server-0.1.2.dist-info/RECORD
