Metadata-Version: 2.4
Name: privy-mcp-server
Version: 0.1.2
Summary: MCP server for Privy.io API - user statistics, wallet management, and authentication
Author-email: Rostislav Tsachev <rtsachev@incentivai.io>
License: MIT
Project-URL: Homepage, https://github.com/incentivai-io/privy-mcp-server
Project-URL: Repository, https://github.com/incentivai-io/privy-mcp-server
Project-URL: Issues, https://github.com/incentivai-io/privy-mcp-server/issues
Keywords: mcp,privy,web3,wallet,blockchain,model-context-protocol
Classifier: Development Status :: 4 - Beta
Classifier: Intended Audience :: Developers
Classifier: License :: OSI Approved :: MIT License
Classifier: Programming Language :: Python :: 3
Classifier: Programming Language :: Python :: 3.10
Classifier: Programming Language :: Python :: 3.11
Classifier: Programming Language :: Python :: 3.12
Classifier: Topic :: Software Development :: Libraries :: Python Modules
Requires-Python: >=3.10
License-File: LICENSE
Requires-Dist: mcp>=1.0.0
Requires-Dist: httpx>=0.27.0
Requires-Dist: python-dotenv>=1.0.0
Provides-Extra: dev
Requires-Dist: pytest>=8.0.0; extra == "dev"
Requires-Dist: pytest-asyncio>=0.23.0; extra == "dev"
Requires-Dist: build>=1.0.0; extra == "dev"
Requires-Dist: twine>=5.0.0; extra == "dev"
Dynamic: license-file
